{
    "2024-02-21": {
        "TSLA": 1,
        "MSFT": 2,
        "MA": 2,
        "HON": 1,
        "CDNS": 2,
        "USB": 1,
        "PSX": 2,
        "AZO": 2,
        "PSA": 1,
        "DLR": 2,
        "SYY": 2,
        "GIS": 1,
        "KMI": 1,
        "DVN": 1,
        "PPL": 1,
        "CLX": 2,
        "TXT": 2,
        "JBHT": 2,
        "MRO": 1,
        "TAP": 1,
        "BLUE": 1,
        "WKHS": 1,
        "APA": 1,
        "TSP": 1,
        "EVGO": 1,
        "BYND": 1,
        "EU": 2,
        "NEOG": 1,
        "ADMA": 2,
        "ABCL": 1,
        "CHKP": 2,
        "ACDC": 1,
        "ZNTL": 1,
        "RLAY": 1,
        "FIVE": 1,
        "TRIN": 1,
        "ASLE": 1,
        "CLDX": 1,
        "PNFP": 1,
        "ABOS": 1,
        "SNBR": 1,
        "IMUX": 1,
        "LOGI": 1,
        "CRMD": 1,
        "PXMD": 1,
        "EXPO": 1,
        "AMTX": 1,
        "NCMI": 1,
        "NOK": 2,
        "BMY": 1,
        "AMC": 1,
        "LYG": 1,
        "ABR": 1,
        "HSY": 2,
        "ACI": 1,
        "UDR": 1,
        "UPS": 1,
        "ES": 1,
        "VSH": 1,
        "ENLC": 1,
        "WTI": 1,
        "LLAP": 1,
        "DTE": 1,
        "PBF": 2,
        "CIG": 1,
        "SXC": 2,
        "OR": 2,
        "LEN": 2,
        "MKC": 1,
        "RY": 1,
        "PRGO": 1,
        "DBI": 2,
        "ASB": 1,
        "NRGV": 1,
        "NJR": 1,
        "SNV": 1,
        "RCUS": 1,
        "SUI": 1,
        "OUST": 1,
        "BSBR": 1,
        "BAK": 1,
        "PGTI": 1,
        "SOL": 1,
        "SLGN": 2,
        "HRTG": 1,
        "DRQ": 1,
        "AVNS": 1
    }
}